skeinrank/__init__.py
skeinrank-0.0.1.dist-info/licenses/LICENSE
skeinrank-0.0.1.dist-info/METADATA
skeinrank-0.0.1.dist-info/WHEEL
skeinrank-0.0.1.dist-info/top_level.txt
skeinrank-0.0.1.dist-info/RECORD
